{
  "JobOrderPart": [
    {
      "DisplayType": "Summary",
      "Differentiator": null,
      "Place": "Content:1"
    },
    {
      "DisplayType": "Detail",
      "Differentiator": null,
      "Place": "Content:1"
    }
  ],
  "CompanyPart": [
    {
      "DisplayType": "Summary",
      "Differentiator": null,
      "Place": "Content:1"
    },
    {
      "DisplayType": "Detail",
      "Differentiator": null,
      "Place": "Content:1"
    }
  ],
  "NewsPart": [
    {
      "DisplayType": "Summary",
      "Differentiator": null,
      "Place": "Content:1"
    },
    {
      "DisplayType": "Detail",
      "Differentiator": null,
      "Place": "Content:1"
    }
  ],
  "CountryPart": [
    {
      "DisplayType": "Summary",
      "Differentiator": null,
      "Place": "Content:1"
    },
    {
      "DisplayType": "Detail",
      "Differentiator": null,
      "Place": "Content:1"
    }
  ],
  "ConsultationPart": [
    {
      "DisplayType": "Summary",
      "Differentiator": null,
      "Place": "Content:1"
    },
    {
      "DisplayType": "Detail",
      "Differentiator": null,
      "Place": "Content:1"
    }
  ],
  "JobOrder": [
    {
      "DisplayType": "Summary",
      "Differentiator": null,
      "Place": "Content:1"
    },
    {
      "DisplayType": "Detail",
      "Differentiator": null,
      "Place": "Content:1"
    }
  ],
  "News": [
    {
      "DisplayType": "Summary",
      "Differentiator": null,
      "Place": "Content:1"
    },
    {
      "DisplayType": "Detail",
      "Differentiator": null,
      "Place": "Content:1"
    }
  ],
  "Company": [
    {
      "DisplayType": "Summary",
      "Differentiator": null,
      "Place": "Content:1"
    },
    {
      "DisplayType": "Detail",
      "Differentiator": null,
      "Place": "Content:1"
    }
  ],
  "Country": [
    {
      "DisplayType": "Summary",
      "Differentiator": null,
      "Place": "Content:1"
    },
    {
      "DisplayType": "Detail",
      "Differentiator": null,
      "Place": "Content:1"
    }
  ],
  "Consultation": [
    {
      "DisplayType": "Summary",
      "Differentiator": null,
      "Place": "Content:1"
    },
    {
      "DisplayType": "Detail",
      "Differentiator": null,
      "Place": "Content:1"
    }
  ],
  "HomePage": [
    {
      "DisplayType": "Detail",
      "Differentiator": null,
      "Place": "Content:1"
    }
  ],
  "JobListings": [
    {
      "DisplayType": "Detail",
      "Differentiator": null,
      "Place": "Content:1"
    }
  ],
  "Menu": [
    {
      "DisplayType": "Detail",
      "Differentiator": "MainMenu",
      "Place": "Navigation:1"
    }
  ],
  "MenuItem": [
    {
      "DisplayType": "Detail",
      "Differentiator": "MainMenu",
      "Place": "Content:1"
    }
  ],
  "MenuItemLink": [
    {
      "DisplayType": "Detail",
      "Differentiator": "MainMenu",
      "Place": "Content:1"
    }
  ],
  "Breadcrumb": [
    {
      "DisplayType": "Detail",
      "Differentiator": null,
      "Place": "Header:5"
    }
  ]
}